{"cameraMode":{"drawMode":0,"name":"Shaded","section":"Shading Mode"},"sceneLighting":true,"audioPlay":false,"sceneViewState":{"m_AlwaysRefresh":false,"showFog":true,"showSkybox":true,"showFlares":true,"showImageEffects":true,"showParticleSystems":true,"showVisualEffectGraphs":true,"m_FxEnabled":true},"in2DMode":false,"pivot":{"x":2082.20068359375,"y":1191.673583984375,"z":710.59521484375},"rotation":{"x":0.062919020652771,"y":-0.10460250079631806,"z":0.0066316137090325359,"w":0.9925028681755066},"size":2101.501220703125,"orthographic":false}